{
  "name": "legend",
  "title": "Legend",
  "description": "Form fieldset legend",
  "icon": "edit",
  "category": "forms",
  "textdomain": "viget-form-blocks",
  "keywords": ["input", "contact", "feedback", "group", "set"],
  "ancestor": ["acf/form"],
  "parent": ["acf/fieldset"],
  "supports": {
    "jsx": true,
    "mode": false,
    "alignWide": false,
    "anchor": true
  },
  "attributes": {
    "blockId": {
      "type": "string",
      "default": ""
    }
  },
  "usesContext": ["acffb/formId", "acffb/fieldsetId"],
  "acf": {
    "mode": "preview"
  }
}
