{
  "name": "fieldset",
  "title": "Fieldset",
  "description": "Form fieldset group",
  "icon": "welcome-widgets-menus",
  "category": "forms",
  "textdomain": "acf-form-blocks",
  "keywords": ["input", "contact", "feedback", "group", "set"],
  "ancestor": ["acf/form"],
  "supports": {
    "jsx": true,
    "mode": false,
    "alignWide": false,
    "anchor": true
  },
  "attributes": {
    "blockId": {
      "type": "string",
      "default": ""
    },
    "groupType": {
      "type": "string",
      "default": "default"
    }
  },
  "providesContext": {
    "acffb/fieldsetId": "blockId"
  },
  "usesContext": ["acffb/formId"],
  "styles": [
    { "name": "default", "label": "List", "isDefault": true },
    { "name": "inline", "label": "Inline" },
    { "name": "columns", "label": "Columns" }
  ],
  "variations": [
    {
      "name": "checkbox-group",
      "icon": "forms",
      "title": "Checkbox Group",
      "scope": ["inserter", "transform"],
      "innerBlocks": [ ["acf/legend"], ["acf/checkbox"], ["acf/checkbox"], ["acf/checkbox"] ],
      "attributes": {
        "groupType": "checkbox"
      },
      "isActive": ["groupType"]
    },
    {
      "name": "address",
      "icon": "location-alt",
      "title": "Address",
      "scope": ["inserter"],
      "innerBlocks": [
        [
          "acf/legend",
          {},
          [
            [
              "core/paragraph",
              {
                "content": "Address"
              }
            ]
          ]
        ],
        [
          "acf/input",
          {},
          [
            [
              "acf/label",
              {},
              [
                [
                  "core/paragraph",
                  {
                    "content": "Address Line 1"
                  }
                ]
              ]
            ]
          ]
        ],
        [
          "acf/input",
          {},
          [
            [
              "acf/label",
              {},
              [
                [
                  "core/paragraph",
                  {
                    "content": "Address Line 2"
                  }
                ],
                [
                  "core/paragraph",
                  {
                    "content": "(optional)",
                    "style": {
                      "elements": {
                        "link": {
                          "color": {
                            "text": "#646464"
                          }
                        }
                      },
                      "color": {
                        "text": "#646464"
                      }
                    }
                  }
                ]
              ]
            ]
          ]
        ],
        [
          "core/columns",
          {},
          [
            [
              "core/column",
              {
                "width": 45
              },
              [
                [
                  "acf/input",
                  {},
                  [
                    [
                      "acf/label",
                      {},
                      [
                        [
                          "core/paragraph",
                          {
                            "content": "City"
                          }
                        ]
                      ]
                    ]
                  ]
                ]
              ]
            ],
            [
              "core/column",
              {
                "width": 20
              },
              [
                [
                  "acf/input",
                  {},
                  [
                    [
                      "acf/label",
                      {},
                      [
                        [
                          "core/paragraph",
                          {
                            "content": "State"
                          }
                        ]
                      ]
                    ]
                  ]
                ]
              ]
            ],
            [
              "core/column",
              {
                "width": 35
              },
              [
                [
                  "acf/input",
                  {},
                  [
                    [
                      "acf/label",
                      {},
                      [
                        [
                          "core/paragraph",
                          {
                            "content": "Zip"
                          }
                        ]
                      ]
                    ]
                  ]
                ]
              ]
            ]
          ]
        ]
      ],
      "attributes": {
        "groupType": "address"
      },
      "isActive": ["groupType"]
    }
  ],
  "style": "file:./style.css",
  "acf": {
    "mode": "preview"
  }
}
